aleph_pytezos/__init__.py
aleph_pytezos/crypto/encoding.py
aleph_pytezos/crypto/key.py
aleph_pytezos-3.13.4.dist-info/LICENSE.txt
aleph_pytezos-3.13.4.dist-info/METADATA
aleph_pytezos-3.13.4.dist-info/WHEEL
aleph_pytezos-3.13.4.dist-info/top_level.txt
aleph_pytezos-3.13.4.dist-info/RECORD
