Metadata-Version: 2.1
Name: aleph-pytezos
Version: 3.13.4
Summary: Add a short description here!
Home-page: https://github.com/pyscaffold/pyscaffold/
Author: Olivier Desenfans
Author-email: desenfans.olivier@gmail.com
License: MIT
Project-URL: Documentation, https://pyscaffold.org/
Platform: any
Classifier: Development Status :: 4 - Beta
Classifier: Programming Language :: Python
License-File: LICENSE.txt
Requires-Dist: base58
Requires-Dist: importlib-metadata
Requires-Dist: mnemonic
Requires-Dist: pynacl
Requires-Dist: python-magic
Requires-Dist: coincurve>=20.0.0
Requires-Dist: typing-extensions
Requires-Dist: fastecdsa
Requires-Dist: pysodium
Provides-Extra: testing
Requires-Dist: pytest; extra == "testing"
Requires-Dist: pytest-cov; extra == "testing"
Requires-Dist: setuptools; extra == "testing"
Requires-Dist: tox; extra == "testing"
Requires-Dist: twine; extra == "testing"
